cursofiap/__init__.py
cursofiap/core.py
cursofiap1_package-1.0.0.dist-info/METADATA
cursofiap1_package-1.0.0.dist-info/WHEEL
cursofiap1_package-1.0.0.dist-info/top_level.txt
cursofiap1_package-1.0.0.dist-info/RECORD
