Metadata-Version: 2.4
Name: cursofiap1-package
Version: 1.0.0
Summary: Descricao da sua lib cursofiap
Home-page: https://github.com/ClaudioMSOliveira/cursofiap
Author: Claudio Marcio S. Oliveira
Author-email: claudiomsoliveira@gmail.com
License: MIT
Dynamic: author
Dynamic: author-email
Dynamic: description
Dynamic: description-content-type
Dynamic: home-page
Dynamic: license
Dynamic: summary
